Metadata-Version: 2.4
Name: altimate-datapilot-cli
Version: 0.2.0
Summary: Assistant for Data Teams
Home-page: https://github.com/AltimateAI/datapilot-cli
Author: Altimate Inc
Author-email: info@altimate.ai
License: MIT
Project-URL: Documentation, https://datapilot.readthedocs.io/
Project-URL: Changelog, https://datapilot.readthedocs.io/en/latest/changelog.html
Project-URL: Issue Tracker, https://github.com/AltimateAI/datapilot-cli/issues
Classifier: Development Status :: 5 - Production/Stable
Classifier: Intended Audience :: Developers
Classifier: License :: OSI Approved :: MIT License
Classifier: Operating System :: Unix
Classifier: Operating System :: POSIX
Classifier: Operating System :: Microsoft :: Windows
Classifier: Programming Language :: Python
Classifier: Programming Language :: Python :: 3
Classifier: Programming Language :: Python :: 3 :: Only
Classifier: Programming Language :: Python :: 3.8
Classifier: Programming Language :: Python :: 3.9
Classifier: Programming Language :: Python :: 3.10
Classifier: Programming Language :: Python :: 3.11
Classifier: Programming Language :: Python :: 3.12
Classifier: Programming Language :: Python :: Implementation :: CPython
Classifier: Programming Language :: Python :: Implementation :: PyPy
Classifier: Topic :: Utilities
Requires-Python: >=3.8
License-File: LICENSE
License-File: AUTHORS.rst
Requires-Dist: click~=8.1.7
Requires-Dist: pydantic<3.0,>=2.0
Requires-Dist: ruamel.yaml~=0.18.6
Requires-Dist: tabulate~=0.9.0
Requires-Dist: requests>=2.31
Requires-Dist: sqlglot~=25.30.0
Requires-Dist: mcp~=1.9.0
Requires-Dist: pyperclip~=1.8.2
Requires-Dist: python-dotenv~=1.0.0
Dynamic: author
Dynamic: author-email
Dynamic: classifier
Dynamic: description
Dynamic: home-page
Dynamic: license
Dynamic: license-file
Dynamic: project-url
Dynamic: requires-dist
Dynamic: requires-python
Dynamic: summary
